AUTHORS
LICENSE
MANIFEST.in
NEWS
README
setup.py
src/HTSQL_DJANGO.egg-info/PKG-INFO
src/HTSQL_DJANGO.egg-info/SOURCES.txt
src/HTSQL_DJANGO.egg-info/dependency_links.txt
src/HTSQL_DJANGO.egg-info/not-zip-safe
src/HTSQL_DJANGO.egg-info/requires.txt
src/HTSQL_DJANGO.egg-info/top_level.txt
src/htsql_django/__init__.py
src/htsql_django/urls.py
src/htsql_django/views.py